{
  "question": "What is the meaning of life?",
  "keywords": [
    "meaning",
    "life",
    "purpose",
    "existence",
    "philosophy"
  ],
  "category": "philosophy",
  "correct_answer": "The meaning of life is one of humanity's most profound questions, with answers varying across cultures, philosophies, and individuals. Common perspectives include finding purpose through relationships, contributing to society, personal growth, spiritual fulfillment, or creating meaning through one's actions and choices. Many philosophers suggest that meaning is not discovered but created through how we choose to live.",
  "timestamp": 1770339793.817871
}