{
  "kind": "conversation_training",
  "timestamp": 1770437500.872694,
  "user": "\"Hmm, that's a great question! I think it's important to consider all possibilities when building on an idea. What if we took it in a completely different direction and explored new possibilities? It could lead to some fascinating innovations!\"",
  "sam_reply": "That's interesting about \"Hmm, that's a great question!. What makes you think that?",
  "improved_reply": null,
  "transcript": "SAM-Beta: How does That's interesting about Building on apply in practice? I'm curious about the implementation.\nSAM-Gamma: Wait, have we considered the edge cases with How does That's interesting about?\nSAM-Delta: Building on Wait, have we considered the - what if we took this in a completely different direction?\nSAM-Alpha: That's interesting about Building on Wait, have we. What makes you think that?\nSAM-Beta: How does That's interesting about Building on apply in practice? I'm curious about the implementation.\nSAM-Gamma: Wait, have we considered the edge cases with How does That's interesting about?\nSAM-Delta: Building on Wait, have we considered the - what if we took this in a completely different direction?\nSAM-Alpha: That's interesting about Building on Wait, have we. What makes you think that?\nSAM-Beta: How does That's interesting about Building on apply in practice? I'm curious about the implementation.\nSAM-Gamma: Wait, have we considered the edge cases with How does That's interesting about?\nSAM-Delta: Building on Wait, have we considered the - what if we took this in a completely different direction?\nSAM-Alpha: That's interesting about Building on Wait, have we. What makes you think that?\nSAM-Beta: How does That's interesting about Building on apply in practice? I'm curious about the implementation.\nSAM-Gamma: Wait, have we considered the edge cases with How does That's interesting about?\nSAM-Delta: \"Hmm, that's a great question! I think it's important to consider all possibilities when building on an idea. What if we took it in a completely different direction and explored new possibilities? It could lead to some fascinating innovations!\"\nSAM-Alpha: That's interesting about \"Hmm, that's a great question!. What makes you think that?",
  "web_snippet": "",
  "teacher_replies": [],
  "muze": {
    "ok": true,
    "training_step": 171,
    "loss": 0.0,
    "value": 0.000552,
    "action": 0,
    "ts": 1770437527.534345,
    "rc": 0,
    "stderr": null
  }
}